sktune/__init__.py
scikit_tune-0.2.2.dist-info/LICENSE
scikit_tune-0.2.2.dist-info/METADATA
scikit_tune-0.2.2.dist-info/WHEEL
scikit_tune-0.2.2.dist-info/top_level.txt
scikit_tune-0.2.2.dist-info/RECORD
