Metadata-Version: 2.1
Name: scikit-tune
Version: 0.2.2
Summary: A friendly way to tune scikit-learn pipelines.
Author: Matheus Couto
Author-email: matheusccouto@gmail.com
License: MIT
License-File: LICENSE
Requires-Dist: optuna
Requires-Dist: scikit-dict
Requires-Dist: pyyaml
